analysis/__init__.py
analysis/analysis_pronounceable.py
analysis/analysis_strength.py
dev/__init__.py
dev/create_pickle.py
kivy_app/__init__.py
kivy_app/main.py
memorable_password/__init__.py
memorable_password/dir.py
memorable_password/mnemonic.py
memorable_password/password.py
memorable_password/policy.py
memorable_password/sentence.py
memorable_password/database/leetspeak.yaml
memorable_password/database/mnemonic.yaml
memorable_password/database/policy.yaml
memorable_password-0.3.0.dist-info/METADATA
memorable_password-0.3.0.dist-info/RECORD
memorable_password-0.3.0.dist-info/WHEEL
memorable_password-0.3.0.dist-info/top_level.txt
pronounceable/__init__.py
pronounceable/complexity.py
pronounceable/components.py
pronounceable/digraph.py
pronounceable/dir.py
pronounceable/main.py
webview/__init__.py
webview/views.py
